psicon/__init__.py
psicon/example.py
psicon-0.0.1.dist-info/METADATA
psicon-0.0.1.dist-info/WHEEL
psicon-0.0.1.dist-info/licenses/LICENSE
psicon-0.0.1.dist-info/RECORD
